ibis_mssqlops/__init__.py
ibis_mssqlops/addibis.py
ibis_mssqlops/addsql.py
ibis_mssqlops/connect.py
ibis_mssqlops/consts.py
ibis_mssqlops/datatypes.py
ibis_mssqlops/expr.py
ibis_mssqlops/funcs.py
ibis_mssqlops/transforms.py
ibis_mssqlops-0.0.58.dist-info/METADATA
ibis_mssqlops-0.0.58.dist-info/WHEEL
ibis_mssqlops-0.0.58.dist-info/RECORD
