Metadata-Version: 2.1
Name: ibis-mssqlops
Version: 0.0.58
Summary: Ibis-mssqlops é uma extensão ao backend MSSQL do ibis-framework
License: MIT
Author: Marcus Holanda
Author-email: mvsh777@hotmail.com
Requires-Python: >=3.11,<4.0
Classifier: Development Status :: 1 - Planning
Classifier: License :: OSI Approved :: MIT License
Classifier: Natural Language :: Portuguese (Brazilian)
Classifier: Programming Language :: PL/SQL
Classifier: Programming Language :: Python :: 3
Classifier: Programming Language :: Python :: 3.11
Classifier: Programming Language :: Python :: 3.12
Requires-Dist: ibis-framework[mssql] (>=8.0.0,<9.0.0)
Requires-Dist: pymssql (>=2.2.11,<3.0.0)
Requires-Dist: sqlalchemy (>=2.0.25,<3.0.0)
Project-URL: Codigo, https://github.com/Marcus-Holanda777/ibis-mssqlops
